aionursery.py
aionursery-0.3.0.dist-info/LICENSE
aionursery-0.3.0.dist-info/WHEEL
aionursery-0.3.0.dist-info/METADATA
aionursery-0.3.0.dist-info/RECORD
