Metadata-Version: 2.1
Name: aionursery
Version: 0.3.0
Summary: Manage background asyncio tasks
Home-page: https://github.com/malinoff/aionursery
Author: Dmitry Malinovsky
Author-email: damalinov@gmail.com
Requires-Python: >=3.5,<4.0
Classifier: License :: OSI Approved :: Apache Software License
Classifier: Programming Language :: Python :: 3
Classifier: Programming Language :: Python :: 3.5
Classifier: Programming Language :: Python :: 3.6
Classifier: Programming Language :: Python :: 3.7
